[
  {
    "id": "01",
    "title": "Commercial Custom Millwork",
    "content": "Custom millwork solutions for commercial spaces, ensuring durability and precision."
  },
  {
    "id": "02",
    "title": "Restaurant Interiors",
    "content": "End-to-end interior solutions designed for functional and inviting dining environments."
  },
  {
    "id": "03",
    "title": "Franchise Finish Packages",
    "content": "Scalable finish packages maintaining brand standards across multiple franchise locations."
  },
  {
    "id": "04",
    "title": "Lobby and Reception Millwork",
    "content": "Custom reception desks and lobby millwork that create a strong first impression."
  },
  {
    "id": "05",
    "title": "Retail Build-Out Finishes",
    "content": "Retail interior finishes and fixtures crafted to enhance the customer experience."
  },
  {
    "id": "06",
    "title": "Shop Drawings",
    "content": "Accurate shop drawings that streamline production and ensure precise execution."
  },
  {
    "id": "07",
    "title": "Kitchen Remodel Materials",
    "content": "Premium material packages for kitchen remodeling, focusing on quality and modern design."
  },
  {
    "id": "08",
    "title": "Bathroom Remodel Materials",
    "content": "High-end renovation materials combining functionality with elegant finishes."
  },
  {
    "id": "09",
    "title": "Flooring Supply & Coordination",
    "content": "Comprehensive flooring solutions, including material sourcing and installation support."
  },
  {
    "id": "10",
    "title": "Finish Carpentry Packages",
    "content": "Complete finish carpentry services delivering precise detailing and craftsmanship."
  }
]
